jolicense/__init__.py
jolicense/license_system.py
jolicense/logger.py
jolicense/settings.py
jolicense-0.1.0.dist-info/METADATA
jolicense-0.1.0.dist-info/WHEEL
jolicense-0.1.0.dist-info/top_level.txt
jolicense-0.1.0.dist-info/RECORD
